yby/__init__.py
yby/y_abondon.py
yby/y_alias.py
yby/y_control.py
yby/y_file.py
yby/y_init.py
yby/y_matplotlib.py
yby/y_mayavi.py
yby/y_package.py
yby/y_sample.py
yby/y_text.py
yby/y_time.py
yby-0.0.51.dist-info/LICENSE.txt
yby-0.0.51.dist-info/METADATA
yby-0.0.51.dist-info/WHEEL
yby-0.0.51.dist-info/top_level.txt
yby-0.0.51.dist-info/RECORD
