Metadata-Version: 2.1
Name: yby
Version: 0.0.51
Summary: yanbingyang personal packages
Home-page: https://pypi.org/user/Flyby_98/
Author: Bingyang Yan
Author-email: yanbingyang1998@outlook.com
License: Copyright (c) 2022 The Python Packaging Authority         
Platform: UNKNOWN
Classifier: Programming Language :: Python :: 3
Classifier: License :: OSI Approved :: MIT License
Classifier: Operating System :: OS Independent
Requires-Python: >=3.6
License-File: LICENSE.txt
Requires-Dist: setuptools
Requires-Dist: wheel
Requires-Dist: twine
Requires-Dist: numpy
Requires-Dist: pandas
Requires-Dist: scipy
Requires-Dist: matplotlib
Requires-Dist: cryptography
Requires-Dist: tqdm
Requires-Dist: glob2
